{
    "eid": "2-s2.0-84922134841",
    "title": "Renormalization group, secular term resummation and AdS (In)stability",
    "cover-date": "2014-10-01",
    "subject-areas": [
        {
            "$": "Nuclear and High Energy Physics",
            "@code": "3106"
        }
    ],
    "keywords": [
        "AdS-CFT Correspondence",
        "Classical Theories of Gravity",
        "Holography and quark-gluon plasmas"
    ],
    "authors": [
        "Ben Craps"
    ],
    "citedby-count": 92,
    "ref-count": 17,
    "ref-list": [
        "Mechanics",
        "Applied Mathematics",
        "Renormalization group and singular perturbations: Multiple scales, boundary layers, and reductive perturbation theory",
        "Mathematical Aspects of Classical and Celestial Mechanics",
        "Holographic interpretation of renormalization group approach to singular perturbations in nonlinear differential equations",
        "Spacetime emergence via holographic RG flow from incompressible Navier-Stokes at the horizon",
        "Weakly turbulent instability of anti-de Sitter spacetime",
        "Gravitational turbulent instability of anti-de Sitter space",
        "On the nonlinear stability of asymptotically anti-de Sitter solutions",
        "Time-periodic solutions in an einstein ads-massless-scalar-field system",
        "Boson stars in AdS spacetime",
        "Holographic relaxation of finite size isolated quantum systems",
        "What drives AdS spacetime unstable?",
        "Holographic thermalization, stability of anti-de sitter space, and the Fermi-Pasta-Ulam paradox",
        "SIAM",
        "Spectral Methods: Algorithms, Analysis and Applications",
        "FORM version 4.0"
    ],
    "affiliation": [
        {
            "affiliation-city": "Brussels",
            "affilname": "International Solvay Institute for Physics and Chemistry",
            "affiliation-country": "Belgium"
        },
        {
            "affiliation-city": "Bangkok",
            "affilname": "Chulalongkorn University",
            "affiliation-country": "Thailand"
        },
        {
            "affiliation-city": "Paris",
            "affilname": "\u00c9cole Normale Sup\u00e9rieure",
            "affiliation-country": "France"
        }
    ],
    "funding": []
}