{
    "eid": "2-s2.0-85112861733",
    "title": "Token allocation for course bidding with machine learning method",
    "cover-date": "2021-05-19",
    "subject-areas": [
        {
            "@_fa": "true",
            "$": "Artificial Intelligence",
            "@code": "1702",
            "@abbrev": "COMP"
        },
        {
            "@_fa": "true",
            "$": "Computer Networks and Communications",
            "@code": "1705",
            "@abbrev": "COMP"
        },
        {
            "@_fa": "true",
            "$": "Hardware and Architecture",
            "@code": "1708",
            "@abbrev": "COMP"
        },
        {
            "@_fa": "true",
            "$": "Information Systems",
            "@code": "1710",
            "@abbrev": "COMP"
        },
        {
            "@_fa": "true",
            "$": "Electrical and Electronic Engineering",
            "@code": "2208",
            "@abbrev": "ENGI"
        },
        {
            "@_fa": "true",
            "$": "Instrumentation",
            "@code": "3105",
            "@abbrev": "PHYS"
        }
    ],
    "keywords": [
        "Artificial Neuron Network",
        "Bid Allocation",
        "Course Bidding",
        "Decision Tree",
        "Random Forest"
    ],
    "authors": [
        "Chonbadee Juthamanee",
        "Krerk Piromsopa",
        "Prabhas Chongstitvatana"
    ],
    "citedby-count": 1,
    "ref-count": 13,
    "ref-list": [
        "Improving the efficiency of course bidding at business schools: Field and laboratory studies",
        "Improvements to auction theory and inventions of new auction formats",
        "A random forest method for real-time price forecasting in New York electricity market",
        "Predicting bid prices by using machine learning methods",
        "A machine-learning approach to optimal bid pricing",
        "Course bidding at business schools",
        "Decision tree methods: Applications for classification and prediction",
        "Big data: New tricks for econometrics",
        "Explained: Neural networks",
        "Trees vs neurons: Comparison between random forest and ann for high-resolution prediction of building energy consumption",
        "A comparison of artificial neural networks and random forests to predict native fish species richness in mediterranean rivers",
        "A comparison of methods for assessing the relative importance of input variables in artificial neural networks"
    ],
    "affiliation": {
        "affiliation-city": "Bangkok",
        "@id": "60028190",
        "affilname": "Chulalongkorn University",
        "@href": "https://api.elsevier.com/content/affiliation/affiliation_id/60028190",
        "affiliation-country": "Thailand"
    },
    "funding": []
}