{
    "eid": "2-s2.0-84923126999",
    "title": "The Great Recession, insurance mandates, and the use of in vitro fertilization services in the United States",
    "cover-date": "2015-02-01",
    "subject-areas": [
        {
            "$": "Obstetrics and Gynecology",
            "@code": "2729"
        },
        {
            "$": "Reproductive Medicine",
            "@code": "2743"
        }
    ],
    "keywords": [
        "Coincident index",
        "economic condition",
        "Great Recession",
        "in vitro fertilization",
        "insurance mandate"
    ],
    "authors": [
        "Sorapop Kiatpongsan"
    ],
    "citedby-count": 7,
    "ref-count": 23,
    "ref-list": [
        "Impact of the 2008-2010 economic recession on local health departments",
        "The Economy and Medical Care",
        "HBS Working Paper",
        "Trends underlying employer-sponsored health insurance growth for americans younger than age Sixty-Five",
        "Impact of the 2008-2009 Economic Recession on Screening Colonoscopy Utilization Among the Insured",
        "Dental usage under changing economic conditions",
        "Research letters: The great recession and racial and ethnic disparities in health services use",
        "The cost of a successful delivery with in vitro fertilization",
        "In vitro fertilization availability and utilization in the United States: a study of demographic, social, and economic factors",
        "Management of the first in vitro fertilization cycle for unexplained infertility: A cost-effectiveness analysis of split in vitro fertilization-intracytoplasmic sperm injection",
        "Expenditures on Children by Families",
        "Insurance coverage and outcomes of in vitro fertilization",
        "Insurance mandates and trends in infertility treatments",
        "The effects of insurance mandates on choices and outcomes in infertility treatment markets",
        "Insurance coverage and in vitro fertilization outcomes: A U.S. perspective",
        "Assisted Reproductive Technology (ART)",
        "United States Census Bureau",
        "State Coincident Indexes",
        "Index of Coincident Economic Indicators",
        "Fed Reserve Bank St Louis",
        "State Infertility Insurance Laws",
        "US Business Cycle Expansions and Contractions",
        "Centers for Disease Control and Prevention"
    ],
    "affiliation": [
        {
            "affiliation-city": "Bangkok",
            "affilname": "Sasin School of Management, Bangkok",
            "affiliation-country": "Thailand"
        },
        {
            "affiliation-city": "Bangkok",
            "affilname": "Chulalongkorn University",
            "affiliation-country": "Thailand"
        },
        {
            "affiliation-city": "Boston",
            "affilname": "Harvard Business School",
            "affiliation-country": "United States"
        },
        {
            "affiliation-city": "Boston",
            "affilname": "Brigham and Women's Hospital",
            "affiliation-country": "United States"
        },
        {
            "affiliation-city": "Cambridge",
            "affilname": "Harvard University",
            "affiliation-country": "United States"
        }
    ],
    "funding": []
}