{
    "eid": "2-s2.0-85137239718",
    "title": "PUBLIC PERCEPTIONS ON TWITTER ABOUT COVID-19 VACCINES IN THAILAND",
    "cover-date": "2022-07-21",
    "subject-areas": [
        {
            "@_fa": "true",
            "$": "Public Health, Environmental and Occupational Health",
            "@code": "2739",
            "@abbrev": "MEDI"
        },
        {
            "@_fa": "true",
            "$": "Infectious Diseases",
            "@code": "2725",
            "@abbrev": "MEDI"
        }
    ],
    "keywords": [
        "COVID-19",
        "sentiment analysis",
        "social media",
        "Twitter",
        "vaccine hesitancy",
        "vaccines"
    ],
    "authors": [
        "Sermsiri Chitphuk",
        "Wasana Stitchantrakul",
        "Boonsong Ongphiphadhanakul",
        "Patipark Kueanjinda",
        "Tassanee Lerksuthirat"
    ],
    "citedby-count": 1,
    "ref-count": 36,
    "ref-list": [
        "Comparative experiments using supervis edlearning and machi ne transl ati on for multilingual sentiment analysis",
        "Improving sentiment anal ysi s over non-Engl i sh Tweets usi ng mul t i l i ngual t r ansf or mer s and automatic translation for data-augmentation",
        "Public perception of t he COVI D-1 9 pa nde mi c on Twitter: sentiment analysis and topic modeling study",
        "The f i r s t 12 mont hs of COVI D-19: a timeline of immunological insights",
        "Matpl otl i b: a 2D graphi cs environment",
        "Ar t i f i c i a l I nt e l l i g e nc e-e na b l e d anal ys i s of publ i c at t i t ude s on F a c e b o o k a n d Twi t t e r t o wa r d COVID-19 vacci nes i n the Uni ted Ki ngdom and t he Uni t ed St at es: observational study",
        "Tracking public attitudes toward COVID-19 vacci nati on on Tweets in Canada: using aspect-based sentiment analysis",
        "An analysis of the Human Papilloma Virus vaccine debate on MySpace blogs",
        "YouTube as a source of i nf or mat i on on i mmuni zat i on: a content analysis",
        "Vacci ne hesi t ancy: underst andi ng bet t er t o address better",
        "A global survey of potential acceptance of a COVID-19 vaccine",
        "Tai l ori ng i n t he di gi t al era: st i mul at i ng di al ogues on heal t h topics in collaboration with social media influencers",
        "How translation alters sentiment",
        "Anal yzi ng t he atti t ude of I ndi an citizens towards COVID-19 vaccine \u2013 a text analytics study",
        "COVID-19 public sentiment insights and machine learning for Tweets classification",
        "Correlates of COVID-19 vaccine hesitancy in Austria: trust and the government",
        "Covid-19: Norway investigates 23 deaths in frail elderly patients after vaccination",
        "Deliberation, dissent, and distrust: understandi ng di sti nct dri vers of coronavi rus di sease 2019 vacci ne hesitancy in the United States",
        "Understanding vaccine hesitancy in COVID-19",
        "Towar ds a machi ne learning approach to the analysis of indirect translation",
        "Twitter sentiment analysis towards COVID-19 vaccines in the Philippines using Na\u00efve Bayes",
        "Comparisons of vaccine hesitancy across five low-and middle-income countries",
        "Seaborn: statistical data visualization"
    ],
    "affiliation": [
        {
            "affiliation-city": "Bangkok",
            "@id": "60015887",
            "affilname": "Faculty of Medicine Ramathibodi Hospital, Mahidol University",
            "@href": "https://api.elsevier.com/content/affiliation/affiliation_id/60015887",
            "affiliation-country": "Thailand"
        },
        {
            "affiliation-city": "Bangkok",
            "@id": "60002620",
            "affilname": "Faculty of Medicine, Chulalongkorn University",
            "@href": "https://api.elsevier.com/content/affiliation/affiliation_id/60002620",
            "affiliation-country": "Thailand"
        }
    ],
    "funding": [
        "Mahi dol University",
        "Mahidol University",
        "National Research Council of Thailand"
    ]
}