{
    "eid": "2-s2.0-85057461681",
    "title": "Developement of Composite Armors Using Natural Rubber Reinforced with Steel Wire Mesh for Ballistic Resistance",
    "cover-date": "2018-11-06",
    "subject-areas": [
        {
            "@_fa": "true",
            "$": "Materials Science (all)",
            "@code": "2500",
            "@abbrev": "MATE"
        },
        {
            "@_fa": "true",
            "$": "Engineering (all)",
            "@code": "2200",
            "@abbrev": "ENGI"
        }
    ],
    "keywords": [],
    "authors": [
        "Seksak Asavavisithchai",
        "Teeranan Marlaiwong",
        "Nuthaporn Nuttayasakul"
    ],
    "citedby-count": 2,
    "ref-count": 12,
    "ref-list": [
        "Impact resistance of fiber metal laminates: A review",
        "Ballistic impact response of laminated composite panels",
        "Ballistic protection mechanisms in personal armour",
        "A numerical study of ply orientation on ballistic impact resistance of multi-ply fabric panels",
        "Studies on ballistic impact of the composite panels",
        "The impact resistance of fiber-metal laminates based on glass fiber reinforced polypropylene",
        "Experimental and numerical investigations on the ballistic performance of polymer matrix composites used in armor design",
        "Puncture resistance of natural rubber latex unidirectional coated fabrics",
        "Study on rubber composite armor anti-shaped charge jet penetration",
        "Effect of fabric stitching on ballistic impact resistance of natural rubber coated fabric systems"
    ],
    "affiliation": {
        "affiliation-city": "Bangkok",
        "@id": "60028190",
        "affilname": "Chulalongkorn University",
        "@href": "https://api.elsevier.com/content/affiliation/affiliation_id/60028190",
        "affiliation-country": "Thailand"
    },
    "funding": []
}