{
    "eid": "2-s2.0-85131472050",
    "title": "Curating the Contemporary in Decolonial Spaces: Observations from Thailand on Curatorial Practice in Southeast Asia",
    "cover-date": "2019-01-01",
    "subject-areas": [
        {
            "@_fa": "true",
            "$": "Arts and Humanities (all)",
            "@code": "1200",
            "@abbrev": "ARTS"
        }
    ],
    "keywords": [
        "Bangkok art biennale",
        "Bangkok biennial",
        "Biennials",
        "Curation",
        "Curatorial practice",
        "Decoloniality",
        "Exhibition histories",
        "Post-curatorial turn",
        "Thai contemporary art",
        "Thailand biennale"
    ],
    "authors": [
        "Gregory Galligan"
    ],
    "citedby-count": 0,
    "ref-count": 36,
    "ref-list": [
        "Notes towards a lexicon of urgencies",
        "Histories of the Asian \u201cnew\u201d: Biennales and contemporary Asian art",
        "The brave new face of art from the East",
        "The black box",
        "Turns in Tropics: Artist-curator",
        "Action research: Generative curatorial practices",
        "Re: Emerge: Towards a new cultural cartography",
        "Asia now",
        "Against curating",
        "Editors\u2019 Letter",
        "The post-occupational condition",
        "Delinking: The rhetoric of modernity, the logic of coloniality and the grammar of de-coloniality",
        "Re: Emerging, decentring and delinking: Shifting the geographies of sensing, believing and knowing",
        "Coloniality is far from over, and so must be decoloniality",
        "Thinking and engaging with the decolonial: A conversation between Walter D. Mignolo and Wanda Nanibush",
        "Thoughts on curatorial practices in the decolonial turn",
        "Contemporary art in Asia: Asia society",
        "The co-dependent curator",
        "Festivalism",
        "Towards the exhibition as research",
        "Von Para zu Post: Aufstieg und Fall des kuratorischen Prinzips (From para to post: The rise and fall of curatorial reason)",
        "Rethinking curatorial colonialism",
        "The art of bliss",
        "Decolonial AestheSis: Colonial wounds/decolonial healings",
        "Destroy to build"
    ],
    "affiliation": {
        "affiliation-city": "Bangkok",
        "@id": "60028190",
        "affilname": "Chulalongkorn University",
        "@href": "https://api.elsevier.com/content/affiliation/affiliation_id/60028190",
        "affiliation-country": "Thailand"
    },
    "funding": []
}