{
    "eid": "2-s2.0-85045119266",
    "title": "Factors influencing achievement of regional league division 2 football tournament management",
    "cover-date": "2018-09-01",
    "subject-areas": [
        {
            "@_fa": "true",
            "$": "Social Sciences (all)",
            "@code": "3300",
            "@abbrev": "SOCI"
        }
    ],
    "keywords": [
        "Achievement",
        "Factors",
        "Football tournament management",
        "Regional League Division 2"
    ],
    "authors": [
        "Piyanut Rattanapian",
        "Juta Tingsabhat",
        "Vijit Kanungsukkasem"
    ],
    "citedby-count": 1,
    "ref-count": 28,
    "ref-list": [
        "Business management tool (Balance Scorecard) helps businesses get real?",
        "\u2018Give me a stadium and I will fill it\u2019: An analysis of the marketing management of Stade Fran\u00e7ais Paris rugby club",
        "Key success factors for strategy implementation in Latin American",
        "The effects of model similarity and model talk on self-efficacy and muscular endurance",
        "Future marketing",
        "Notes on a theory of organization",
        "Scouting center for youth with sports talent. Association of Sports Authority of Thailand",
        "Scouting and development of youth with sport talent"
    ],
    "affiliation": {
        "affiliation-city": "Bangkok",
        "@id": "60028190",
        "affilname": "Chulalongkorn University",
        "@href": "https://api.elsevier.com/content/affiliation/affiliation_id/60028190",
        "affiliation-country": "Thailand"
    },
    "funding": []
}