{
    "eid": "2-s2.0-85084966821",
    "title": "Mixed Integer I.inear Programming (MILP) algorithm study for petrochemical industry supply chain",
    "cover-date": "2018-01-01",
    "subject-areas": [
        {
            "@_fa": "true",
            "$": "Chemical Engineering (miscellaneous)",
            "@code": "1501",
            "@abbrev": "CENG"
        },
        {
            "@_fa": "true",
            "$": "Process Chemistry and Technology",
            "@code": "1508",
            "@abbrev": "CENG"
        }
    ],
    "keywords": [],
    "authors": [
        "F. Titawat",
        "S. Kitipat"
    ],
    "citedby-count": 0,
    "ref-count": 2,
    "ref-list": [],
    "affiliation": {
        "affiliation-city": "Bangkok",
        "@id": "60028190",
        "affilname": "Chulalongkorn University",
        "@href": "https://api.elsevier.com/content/affiliation/affiliation_id/60028190",
        "affiliation-country": "Thailand"
    },
    "funding": []
}