{
    "eid": "2-s2.0-85099870535",
    "title": "Erratum to \u2018Effect of strontium and zirconium doped barium cerate on the performance of proton ceramic electrolyser cell for syngas production from carbon dioxide and steam\u2019 [Int J Hydrogen Energy 44 (2019) 20634\u201320640] (International Journal of Hydrogen Energy (2019) 44(37) (20634\u201320640), (S0360319918323450), (10.1016/j.ijhydene.2018.07.121))",
    "cover-date": "2021-02-19",
    "subject-areas": [
        {
            "@_fa": "true",
            "$": "Renewable Energy, Sustainability and the Environment",
            "@code": "2105",
            "@abbrev": "ENER"
        },
        {
            "@_fa": "true",
            "$": "Fuel Technology",
            "@code": "2103",
            "@abbrev": "ENER"
        },
        {
            "@_fa": "true",
            "$": "Condensed Matter Physics",
            "@code": "3104",
            "@abbrev": "PHYS"
        },
        {
            "@_fa": "true",
            "$": "Energy Engineering and Power Technology",
            "@code": "2102",
            "@abbrev": "ENER"
        }
    ],
    "keywords": [],
    "authors": [
        "J. Sarabut",
        "S. Charojrochkul",
        "T. Sornchamni",
        "N. Laosiripojana",
        "S. Assabumrungrat",
        "U. W. Hartley",
        "P. Kim-Lohsoontorn"
    ],
    "citedby-count": 0,
    "ref-count": 0,
    "ref-list": [],
    "affiliation": [
        {
            "affiliation-city": "Bangkok",
            "@id": "60114641",
            "affilname": "PTT Public Company Limited",
            "@href": "https://api.elsevier.com/content/affiliation/affiliation_id/60114641",
            "affiliation-country": "Thailand"
        },
        {
            "affiliation-city": "Bangkok",
            "@id": "60103462",
            "affilname": "King Mongkut's University of Technology North Bangkok",
            "@href": "https://api.elsevier.com/content/affiliation/affiliation_id/60103462",
            "affiliation-country": "Thailand"
        },
        {
            "affiliation-city": "Bangkok",
            "@id": "60028190",
            "affilname": "Chulalongkorn University",
            "@href": "https://api.elsevier.com/content/affiliation/affiliation_id/60028190",
            "affiliation-country": "Thailand"
        },
        {
            "affiliation-city": "Pathum Thani",
            "@id": "60014471",
            "affilname": "Thailand National Metal and Materials Technology Center",
            "@href": "https://api.elsevier.com/content/affiliation/affiliation_id/60014471",
            "affiliation-country": "Thailand"
        },
        {
            "affiliation-city": "Nakhon Pathom",
            "@id": "60012718",
            "affilname": "Mahidol University",
            "@href": "https://api.elsevier.com/content/affiliation/affiliation_id/60012718",
            "affiliation-country": "Thailand"
        },
        {
            "affiliation-city": "Thonburi",
            "@id": "60008786",
            "affilname": "King Mongkut's University of Technology Thonburi",
            "@href": "https://api.elsevier.com/content/affiliation/affiliation_id/60008786",
            "affiliation-country": "Thailand"
        }
    ],
    "funding": []
}