{
    "eid": "2-s2.0-85113346112",
    "title": "Robustness of the cosmological constant damping mechanism through matter eras",
    "cover-date": "2021-09-01",
    "subject-areas": [
        {
            "@_fa": "true",
            "$": "Physics and Astronomy (miscellaneous)",
            "@code": "3101",
            "@abbrev": "PHYS"
        }
    ],
    "keywords": [
        "Cosmological constant problem",
        "Cosmology",
        "Naturalness",
        "Scalar-tensor theory"
    ],
    "authors": [
        "Oleg Evnin",
        "Victor Massart",
        "K\u00e9vin Nguyen"
    ],
    "citedby-count": 1,
    "ref-count": 45,
    "ref-list": [
        "Everything you always wanted to know about the cosmological constant problem (but were afraid to ask)",
        "(Planck Collaboration) 2020 Planck 2018 results. VI Cosmological parameters",
        "Relaxing the cosmological constant: A proof of concept",
        "The well-tempered cosmological constant",
        "Well-tempered cosmology",
        "Cosmological cancellation of the vacuum energy density",
        "On the cosmological constant problem",
        "Local self-tuning mechanism for the cosmological constant",
        "Cosmological self-tuning and local solutions in generalized Horndeski theories",
        "Unified approach to cosmic acceleration",
        "A class of effective field theory models of cosmic acceleration",
        "The effective field theory of dark energy",
        "Dark energy or modified gravity? An effective field theory approach",
        "Essential building blocks of dark energy",
        "Screening and degenerate kinetic self-acceleration from the nonlinear freedom of reconstructed Horndeski theories",
        "Graceful exit for the cosmological constant damping scenario",
        "An attempt to get rid of the cosmological constant",
        "Cosmological-constant damping by unstable scalar fields",
        "Field model with a dynamic cancellation of the cosmological constant",
        "Damping of the cosmological constant by a classical scalar field",
        "Attempt at a classical cancellation of the cosmological constant",
        "Classical cancellation of the cosmological constant reconsidered",
        "Higher spin fields and the problem of the cosmological constant",
        "Ruling out a higher spin field solution to the cosmological constant problem",
        "Reconsidering a higher-spin-field solution to the main cosmological constant problem",
        "Vector-field model with compensated cosmological constant and radiation-dominated FRWphase",
        "Possible solution to the main cosmological constant problem",
        "Dynamical vacuum energy via adjustment mechanism",
        "Tensor-scalar cosmological models and their relaxation toward general relativity",
        "Tensor-multi-scalar theories of gravitation Class",
        "Reconstruction of a scalar-tensor theory of gravity in an accelerating Universe",
        "Mars high resolution gravity fields fromMRO, Mars seasonal gravity, and other dynamical parameters",
        "Relativistic effects and dark matter in the Solar system from observations of planets and spacecraft",
        "A test of general relativity using radio links with the Cassini spacecraft",
        "Large magellanic cloud cepheid standards provide a 1% foundation for the determination of the Hubble constant and stronger evidence for physics beyond",
        "Tensions between the early and late Universe",
        "H0LiCOW-XIII. A 2.4 per cent measurement of H0 from lensed quasars: 5.3\u03c3 tension between early- and late-Universe probes",
        "Large mass hierarchy from a small nonminimal coupling"
    ],
    "affiliation": [
        {
            "affiliation-city": "Bangkok",
            "@id": "60028190",
            "affilname": "Chulalongkorn University",
            "@href": "https://api.elsevier.com/content/affiliation/affiliation_id/60028190",
            "affiliation-country": "Thailand"
        },
        {
            "affiliation-city": "Brussels",
            "@id": "60026810",
            "affilname": "Vrije Universiteit Brussel",
            "@href": "https://api.elsevier.com/content/affiliation/affiliation_id/60026810",
            "affiliation-country": "Belgium"
        },
        {
            "affiliation-city": "London",
            "@id": "60011520",
            "affilname": "King's College London",
            "@href": "https://api.elsevier.com/content/affiliation/affiliation_id/60011520",
            "affiliation-country": "United Kingdom"
        },
        {
            "affiliation-city": "Cambridge",
            "@id": "60009982",
            "affilname": "Harvard University",
            "@href": "https://api.elsevier.com/content/affiliation/affiliation_id/60009982",
            "affiliation-country": "United States"
        },
        {
            "affiliation-city": "Montreal",
            "@id": "60009507",
            "affilname": "University of Montreal",
            "@href": "https://api.elsevier.com/content/affiliation/affiliation_id/60009507",
            "affiliation-country": "Canada"
        }
    ],
    "funding": []
}