{
    "eid": "2-s2.0-84995553644",
    "title": "Ultrasound diagnosis",
    "cover-date": "2016-01-01",
    "subject-areas": [
        {
            "$": "General Veterinary",
            "@code": "3400"
        }
    ],
    "keywords": [],
    "authors": [
        "Phiwipha Kamonrat"
    ],
    "citedby-count": 0,
    "ref-count": 2,
    "ref-list": [
        "Ultrasound-guided catheter biopsy of the lower urinary tract: Technique and results in 12 dogs",
        "SONOGRAPHIC INVESTIGATION OF TRANSITIONAL CELL CARCINOMA OF THE URINARY BLADDER IN SMALL ANIMALS"
    ],
    "affiliation": {
        "affiliation-city": "Bangkok",
        "affilname": "Chulalongkorn University",
        "affiliation-country": "Thailand"
    },
    "funding": []
}