{
    "eid": "2-s2.0-85026784306",
    "title": "Pulsed DC magnetron sputtering deposition of crystalline photocatalytic titania coatings at elevated process pressures",
    "cover-date": "2017-11-15",
    "subject-areas": [
        {
            "$": "Condensed Matter Physics",
            "@code": "3104"
        },
        {
            "$": "Mechanical Engineering",
            "@code": "2210"
        },
        {
            "$": "Mechanics of Materials",
            "@code": "2211"
        },
        {
            "$": "General Materials Science",
            "@code": "2500"
        }
    ],
    "keywords": [
        "Magnetron sputtering",
        "Methylene blue",
        "N-doping",
        "Pressure effect",
        "Stearic acid",
        "Titanium dioxide"
    ],
    "authors": [
        "Marina Ratova"
    ],
    "citedby-count": 16,
    "ref-count": 35,
    "ref-list": [
        "Photosensitized Electrolytic Oxidation on Semiconducting n-Type TiO2 Electrode",
        "Recent developments in titanium oxide-based photocatalysts",
        "A review on the visible light active titanium dioxide photocatalysts for environmental applications",
        "Titanium dioxide photocatalysis: present situation and future approaches",
        "Titanium oxide based visible light photocatalysts: Materials design and applications",
        null,
        "Enhanced properties of magnetron sputtered photocatalytic coatings via transition metal doping",
        "Synergistic effect of doping with nitrogen and molybdenum on the photocatalytic properties of thin titania films",
        "Magnetron sputtering: A review of recent developments and applications",
        "Optimisation of HiPIMS photocatalytic titania coatings for low temperature deposition",
        "Deposition of photocatalytic titania coatings on polymeric substrates by HiPIMS",
        "HiPIMS deposition of tungsten-doped titania coatings for photocatalytic applications",
        "Structural formation and photocatalytic activity of magnetron sputtered titania and doped-titania coatings",
        null,
        null,
        null,
        null,
        null,
        null,
        null,
        null,
        "Visible-light photocatalysis in nitrogen-doped titanium oxides",
        "Optical Properties and Electronic Structure of Amorphous Germanium",
        null,
        "Optimization studies of photocatalytic tungsten-doped titania coatings deposited by reactive magnetron co-sputtering",
        "Ti 2p and O 1s core levels and chemical bonding in titanium-bearing oxides",
        "Study of the bandgap of synthesized titanium dioxide nanoparticules using the sol-gel method and a hydrothermal treatment",
        null,
        null,
        null,
        "The distribution of ion energies at the substrate in an asymmetric bi-polar pulsed DC magnetron discharge",
        "The influence of pulse frequency and duty on the deposition rate in pulsed magnetron sputtering",
        null,
        null,
        null
    ],
    "affiliation": [
        {
            "affiliation-city": "Bangkok",
            "affilname": "Chulalongkorn University",
            "affiliation-country": "Thailand"
        },
        {
            "affiliation-city": "Manchester",
            "affilname": "Manchester Metropolitan University",
            "affiliation-country": "United Kingdom"
        }
    ],
    "funding": [
        "Manchester Metropolitan University",
        "Thailand Research Fund"
    ]
}