{
    "eid": "2-s2.0-85022048334",
    "title": "Modeling of root-reinforced soil slope under rainfall condition",
    "cover-date": "2017-06-15",
    "subject-areas": [
        {
            "$": "General Engineering",
            "@code": "2200"
        }
    ],
    "keywords": [
        "Centrifuge modeling",
        "Landslides",
        "Seepage analysis",
        "Slope stability",
        "Vegetation"
    ],
    "authors": [
        "Suched Likitlersuang"
    ],
    "citedby-count": 38,
    "ref-count": 23,
    "ref-list": [
        "A Numerical Investigation of the Stability of Unsaturated Soil Slopes Subjected to Transient Seepage",
        "Slope Stability",
        "Use of Vegetation in Civil Engineering Construction Industry and Research Information Association (CIRIA",
        "Slope Stabilization and Erosion Control",
        "Biotechnical and Soil Bioengineering Slope Stabilization: A Practical Guide for Erosion Control",
        "Shear strength of a soil containing vegetation roots",
        "STRENGTH OF TREE ROOTS AND LANDSLIDES ON PRICE OF WALES ISLAND, ALASKA.",
        "Proceedings of the First International Conference on Vetiver, Office of the Royal Development Projects Board, Bangkok",
        "A Study on the Ecotype Comparison of Vetiver Grass in Thailand",
        "Laboratory and modelling investigation of root-reinforced system for slope stabilisation",
        "Centrifuge modelling of soil slopes reinforced with vegetation",
        "Centrifuge modelling of soil slopes containing model plant roots",
        "Causative mechanisms of rainfall-induced fill slope failures",
        "Centrifuge model simulations of rainfall-induced slope instability",
        "On the seepage-induced failure of vegetation-stabilised slopes",
        "Centrifuge modelling of root-reinforced soil slope subjected to rainfall infiltration",
        "A novel root system for simulating transpiration-induced soil suction in centrifuge",
        "Centrifuge modelling of the effects of root geometry on transpiration-induced suction and stability of vegetated slopes",
        "Effects of root geometry and transpiration on pull-out resistance",
        "Geotechnical Centrifuge Technology",
        "An objective classification of rainfall events on the basis of their convective features: Application to rainfall intensity in the Northeast of Spain",
        "Version\u2014An Engineering Methodology",
        "A model to predict the water retention curve from basic geotechnical properties"
    ],
    "affiliation": [
        {
            "affiliation-city": "Tokyo",
            "affilname": "Institute of Science Tokyo",
            "affiliation-country": "Japan"
        },
        {
            "affiliation-city": "Bangkok",
            "affilname": "Chulalongkorn University",
            "affiliation-country": "Thailand"
        }
    ],
    "funding": [
        "Thailand Research Fund",
        "Thailand Research Fund"
    ]
}