{
    "eid": "2-s2.0-85164305739",
    "title": "Precarity and social protection of migrant fishers in Thailand: Case studies of death and disappearance at sea",
    "cover-date": "2023-09-01",
    "subject-areas": [
        {
            "@_fa": "true",
            "$": "Aquatic Science",
            "@code": "1104",
            "@abbrev": "AGRI"
        },
        {
            "@_fa": "true",
            "$": "Environmental Science (all)",
            "@code": "2300",
            "@abbrev": "ENVI"
        },
        {
            "@_fa": "true",
            "$": "Economics and Econometrics",
            "@code": "2002",
            "@abbrev": "ECON"
        },
        {
            "@_fa": "true",
            "$": "Management, Monitoring, Policy and Law",
            "@code": "2308",
            "@abbrev": "ENVI"
        },
        {
            "@_fa": "true",
            "$": "Law",
            "@code": "3308",
            "@abbrev": "SOCI"
        }
    ],
    "keywords": [
        "Death and disappearance",
        "Fishing industry",
        "Social Protection",
        "Thailand",
        "Welfare Committee"
    ],
    "authors": [
        "Supang Chantavanich",
        "Waranya Jitpong"
    ],
    "citedby-count": 0,
    "ref-count": 44,
    "ref-list": [
        "Acts of Resistance",
        "Already the most dangerous profession, fisheries facing an increasing drug-use problem",
        "Under the shadow: forced labour among sea fishers in Thailand",
        "Decent work in fisheries: current trends and key considerations for future research and policy",
        "International transparency obligations in fisheries conservation and management: Inter-state and intra-state dimensions",
        "Ship to Shore Rights: Baseline Research Findings on Fishers and Seafood Workers in Thailand",
        "Precarity",
        "Situation on Migrant Workers and Border Crossing During the Covid-19 Pandemic",
        "COVID-19, instability and migrant fish workers in Asia",
        "Identification of unidentified migrant workers' dead in Thailand",
        "Time For a Sea Change: why union rights for migrant workers are needed to prevent forced labor in the Thai seafood industry",
        "Social Protection, Development, and Migration: challenges and prospects",
        "Impacts of the COVID-19 pandemic on small-scale producers and workers: perspectives from Thailand's seafood supply chain",
        "New Zealand's turbulent waters: the use of forced labour in the fishing industry",
        "Co-creating changes to achieve decent work conditions in the New Zealand fishing industry",
        "Beyond' slavery scandals': explaining working conditions among fish workers in Taiwan and Thailand",
        "The Political Economy of the Small Welfare State in South Korea"
    ],
    "affiliation": {
        "affiliation-city": "Bangkok",
        "@id": "60028190",
        "affilname": "Chulalongkorn University",
        "@href": "https://api.elsevier.com/content/affiliation/affiliation_id/60028190",
        "affiliation-country": "Thailand"
    },
    "funding": []
}